{
  "version": "1.18.2",
  "minimumCoreVersion": "5.2.0",
  "protocol": "https",
  "host": "chanjoke.intellisoftkenya.com",
  "hostPath": "",
  "port": "",
  "title": "ChanjoKE HIM Console",
  "footerTitle": "OpenHIM Administration Console",
  "footerPoweredBy": "<a href='http://openhim.org/' target='_blank'>Powered by OpenHIM</a>",
  "loginBanner": "",
  "mediatorLastHeartbeatWarningSeconds": 60,
  "mediatorLastHeartbeatDangerSeconds": 120,
  "showLoginForm": false,
  "ssoEnabled": true,
  "keyCloakUrl": "https://chanjokeiam.intellisoftkenya.com",
  "keyCloakRealm": "master",
  "keyCloakClientId": "openhim-oauth"
}
